geodeep/__init__.py
geodeep/ckdtree.py
geodeep/debug.py
geodeep/detection.py
geodeep/geodeep.py
geodeep/inference.py
geodeep/models.py
geodeep/segmentation.py
geodeep/slidingwindow.py
geodeep/utils.py
geodeep/scripts/__init__.py
geodeep/scripts/convert_retinanet_to_onnx.py
geodeep/scripts/inspect_model.py
geodeep/scripts/main.py
geodeep/scripts/yolo2geodeep.py
geodeep-0.9.11.dist-info/METADATA
geodeep-0.9.11.dist-info/WHEEL
geodeep-0.9.11.dist-info/entry_points.txt
geodeep-0.9.11.dist-info/licenses/LICENSE
geodeep-0.9.11.dist-info/RECORD
