Metadata-Version: 2.4
Name: geodeep
Version: 0.9.11
Summary: Free and open source library for AI object detection and semantic segmentation in geospatial rasters
Project-URL: Homepage, https://github.com/uav4geo/GeoDeep
Project-URL: Source, https://github.com/uav4geo/GeoDeep
Project-URL: Documentation, https://github.com/uav4geo/GeoDeep
Project-URL: Tracker, https://github.com/uav4geo/GeoDeep/issues
Project-URL: History, https://github.com/uav4geo/GeoDeep/releases
Author: GeoDeep Authors
Author-email: Piero Toffanin <pt@uav4geo.com>
Maintainer: GeoDeep Authors
Maintainer-email: Piero Toffanin <pt@uav4geo.com>
License:                     GNU AFFERO GENERAL PUBLIC LICENSE
License-File: LICENSE
Keywords: Python,geospatial,geotiff,object-detection,semantic-segmentation
Classifier: License :: OSI Approved :: GNU Affero General Public License v3
Classifier: Operating System :: OS Independent
Classifier: Programming Language :: Python :: 3
Classifier: Programming Language :: Python :: 3.6
Classifier: Programming Language :: Python :: 3.7
Classifier: Programming Language :: Python :: 3.8
Classifier: Programming Language :: Python :: 3.9
Classifier: Programming Language :: Python :: 3.10
Classifier: Programming Language :: Python :: 3.11
Classifier: Programming Language :: Python :: 3.12
Requires-Python: >=3.6
Requires-Dist: onnxruntime>=1.10.0
Requires-Dist: rasterio>=1.2.9
Provides-Extra: dev
Requires-Dist: onnx>=1.17.0; extra == 'dev'
Requires-Dist: onnxsim>=0.4.36; extra == 'dev'
Requires-Dist: pillow>=11.1.0; extra == 'dev'
Requires-Dist: torch>=2.5.1; extra == 'dev'
Provides-Extra: docs
Requires-Dist: sphinx-autobuild>=2024.10.3; extra == 'docs'
Requires-Dist: sphinx>=8.1.3; extra == 'docs'
Provides-Extra: test
Requires-Dist: pytest>=7.2.0; extra == 'test'
